[{"match":{"id":224735633,"tournament_id":9325369,"state":"complete","player1_id":138064894,"player2_id":138064888,"player1_prereq_match_id":null,"player2_prereq_match_id":null,"player1_is_prereq_match_loser":false,"player2_is_prereq_match_loser":false,"winner_id":138064894,"loser_id":138064888,"started_at":"2021-01-15T21:32:06.010-06:00","created_at":"2021-01-15T21:32:05.354-06:00","updated_at":"2021-01-15T21:54:22.242-06:00","identifier":"A","has_attachment":false,"round":1,"player1_votes":null,"player2_votes":null,"group_id":null,"attachment_count":null,"scheduled_time":null,"location":null,"underway_at":null,"optional":false,"rushb_id":null,"completed_at":"2021-01-15T21:54:22.279-06:00","suggested_play_order":1,"forfeited":null,"open_graph_image_file_name":null,"open_graph_image_content_type":null,"open_graph_image_file_size":null,"prerequisite_match_ids_csv":"","scores_csv":"3-1"}},{"match":{"id":224735634,"tournament_id":9325369,"state":"complete","player1_id":138064895,"player2_id":138064892,"player1_prereq_match_id":null,"player2_prereq_match_id":null,"player1_is_prereq_match_loser":false,"player2_is_prereq_match_loser":false,"winner_id":138064895,"loser_id":138064892,"started_at":"2021-01-15T21:32:06.165-06:00","created_at":"2021-01-15T21:32:05.360-06:00","updated_at":"2021-01-15T21:54:28.606-06:00","identifier":"B","has_attachment":false,"round":1,"player1_votes":null,"player2_votes":null,"group_id":null,"attachment_count":null,"scheduled_time":null,"location":null,"underway_at":null,"optional":false,"rushb_id":null,"completed_at":"2021-01-15T21:54:28.647-06:00","suggested_play_order":2,"forfeited":null,"open_graph_image_file_name":null,"open_graph_image_content_type":null,"open_graph_image_file_size":null,"prerequisite_match_ids_csv":"","scores_csv":"3-1"}},{"match":{"id":224735635,"tournament_id":9325369,"state":"complete","player1_id":138064896,"player2_id":138065160,"player1_prereq_match_id":null,"player2_prereq_match_id":null,"player1_is_prereq_match_loser":false,"player2_is_prereq_match_loser":false,"winner_id":138064896,"loser_id":138065160,"started_at":"2021-01-15T21:32:06.180-06:00","created_at":"2021-01-15T21:32:05.366-06:00","updated_at":"2021-01-15T22:31:55.925-06:00","identifier":"C","has_attachment":false,"round":1,"player1_votes":null,"player2_votes":null,"group_id":null,"attachment_count":null,"scheduled_time":null,"location":null,"underway_at":null,"optional":false,"rushb_id":null,"completed_at":"2021-01-15T22:31:55.969-06:00","suggested_play_order":3,"forfeited":null,"open_graph_image_file_name":null,"open_graph_image_content_type":null,"open_graph_image_file_size":null,"prerequisite_match_ids_csv":"","scores_csv":"3-2"}},{"match":{"id":224735636,"tournament_id":9325369,"state":"complete","player1_id":138064889,"player2_id":138068477,"player1_prereq_match_id":null,"player2_prereq_match_id":null,"player1_is_prereq_match_loser":false,"player2_is_prereq_match_loser":false,"winner_id":138064889,"loser_id":138068477,"started_at":"2021-01-15T21:32:06.191-06:00","created_at":"2021-01-15T21:32:05.375-06:00","updated_at":"2021-01-15T21:53:08.653-06:00","identifier":"D","has_attachment":false,"round":1,"player1_votes":null,"player2_votes":null,"group_id":null,"attachment_count":null,"scheduled_time":null,"location":null,"underway_at":null,"optional":false,"rushb_id":null,"completed_at":"2021-01-15T21:53:08.724-06:00","suggested_play_order":4,"forfeited":null,"open_graph_image_file_name":null,"open_graph_image_content_type":null,"open_graph_image_file_size":null,"prerequisite_match_ids_csv":"","scores_csv":"3-1"}},{"match":{"id":224735637,"tournament_id":9325369,"state":"complete","player1_id":138064899,"player2_id":138068562,"player1_prereq_match_id":null,"player2_prereq_match_id":null,"player1_is_prereq_match_loser":false,"player2_is_prereq_match_loser":false,"winner_id":138064899,"loser_id":138068562,"started_at":"2021-01-15T21:32:06.203-06:00","created_at":"2021-01-15T21:32:05.468-06:00","updated_at":"2021-01-15T22:06:04.101-06:00","identifier":"E","has_attachment":false,"round":1,"player1_votes":null,"player2_votes":null,"group_id":null,"attachment_count":null,"scheduled_time":null,"location":null,"underway_at":null,"optional":false,"rushb_id":null,"completed_at":"2021-01-15T22:06:04.147-06:00","suggested_play_order":5,"forfeited":null,"open_graph_image_file_name":null,"open_graph_image_content_type":null,"open_graph_image_file_size":null,"prerequisite_match_ids_csv":"","scores_csv":"3-2"}},{"match":{"id":224735638,"tournament_id":9325369,"state":"complete","player1_id":138064901,"player2_id":138064894,"player1_prereq_match_id":null,"player2_prereq_match_id":224735633,"player1_is_prereq_match_loser":false,"player2_is_prereq_match_loser":false,"winner_id":138064901,"loser_id":138064894,"started_at":"2021-01-15T21:54:22.258-06:00","created_at":"2021-01-15T21:32:05.477-06:00","updated_at":"2021-01-15T22:06:54.844-06:00","identifier":"F","has_attachment":false,"round":2,"player1_votes":null,"player2_votes":null,"group_id":null,"attachment_count":null,"scheduled_time":null,"location":null,"underway_at":null,"optional":false,"rushb_id":null,"completed_at":"2021-01-15T22:06:54.876-06:00","suggested_play_order":9,"forfeited":null,"open_graph_image_file_name":null,"open_graph_image_content_type":null,"open_graph_image_file_size":null,"prerequisite_match_ids_csv":"224735633","scores_csv":"3-0"}},{"match":{"id":224735639,"tournament_id":9325369,"state":"complete","player1_id":138064900,"player2_id":138064886,"player1_prereq_match_id":null,"player2_prereq_match_id":null,"player1_is_prereq_match_loser":false,"player2_is_prereq_match_loser":false,"winner_id":138064900,"loser_id":138064886,"started_at":"2021-01-15T21:32:06.223-06:00","created_at":"2021-01-15T21:32:05.483-06:00","updated_at":"2021-01-15T22:00:30.683-06:00","identifier":"G","has_attachment":false,"round":2,"player1_votes":null,"player2_votes":null,"group_id":null,"attachment_count":null,"scheduled_time":null,"location":null,"underway_at":null,"optional":false,"rushb_id":null,"completed_at":"2021-01-15T22:00:30.732-06:00","suggested_play_order":6,"forfeited":null,"open_graph_image_file_name":null,"open_graph_image_content_type":null,"open_graph_image_file_size":null,"prerequisite_match_ids_csv":"","scores_csv":"3-2"}},{"match":{"id":224735640,"tournament_id":9325369,"state":"complete","player1_id":138064897,"player2_id":138064895,"player1_prereq_match_id":null,"player2_prereq_match_id":224735634,"player1_is_prereq_match_loser":false,"player2_is_prereq_match_loser":false,"winner_id":138064897,"loser_id":138064895,"started_at":"2021-01-15T21:54:28.631-06:00","created_at":"2021-01-15T21:32:05.488-06:00","updated_at":"2021-01-15T22:08:15.134-06:00","identifier":"H","has_attachment":false,"round":2,"player1_votes":null,"player2_votes":null,"group_id":null,"attachment_count":null,"scheduled_time":null,"location":null,"underway_at":null,"optional":false,"rushb_id":null,"completed_at":"2021-01-15T22:08:15.157-06:00","suggested_play_order":10,"forfeited":null,"open_graph_image_file_name":null,"open_graph_image_content_type":null,"open_graph_image_file_size":null,"prerequisite_match_ids_csv":"224735634","scores_csv":"3-0"}},{"match":{"id":224735641,"tournament_id":9325369,"state":"complete","player1_id":138064887,"player2_id":138064896,"player1_prereq_match_id":null,"player2_prereq_match_id":224735635,"player1_is_prereq_match_loser":false,"player2_is_prereq_match_loser":false,"winner_id":138064887,"loser_id":138064896,"started_at":"2021-01-15T22:31:55.948-06:00","created_at":"2021-01-15T21:32:05.492-06:00","updated_at":"2021-01-15T22:58:16.553-06:00","identifier":"I","has_attachment":false,"round":2,"player1_votes":null,"player2_votes":null,"group_id":null,"attachment_count":null,"scheduled_time":null,"location":null,"underway_at":null,"optional":false,"rushb_id":null,"completed_at":"2021-01-15T22:58:16.624-06:00","suggested_play_order":11,"forfeited":false,"open_graph_image_file_name":null,"open_graph_image_content_type":null,"open_graph_image_file_size":null,"prerequisite_match_ids_csv":"224735635","scores_csv":"3-0"}},{"match":{"id":224735642,"tournament_id":9325369,"state":"complete","player1_id":138064898,"player2_id":138064889,"player1_prereq_match_id":null,"player2_prereq_match_id":224735636,"player1_is_prereq_match_loser":false,"player2_is_prereq_match_loser":false,"winner_id":138064898,"loser_id":138064889,"started_at":"2021-01-15T21:53:08.694-06:00","created_at":"2021-01-15T21:32:05.496-06:00","updated_at":"2021-01-15T22:09:33.489-06:00","identifier":"J","has_attachment":false,"round":2,"player1_votes":null,"player2_votes":null,"group_id":null,"attachment_count":null,"scheduled_time":null,"location":null,"underway_at":null,"optional":false,"rushb_id":null,"completed_at":"2021-01-15T22:09:33.521-06:00","suggested_play_order":12,"forfeited":null,"open_graph_image_file_name":null,"open_graph_image_content_type":null,"open_graph_image_file_size":null,"prerequisite_match_ids_csv":"224735636","scores_csv":"3-1"}},{"match":{"id":224735643,"tournament_id":9325369,"state":"complete","player1_id":138064890,"player2_id":138064891,"player1_prereq_match_id":null,"player2_prereq_match_id":null,"player1_is_prereq_match_loser":false,"player2_is_prereq_match_loser":false,"winner_id":138064890,"loser_id":138064891,"started_at":"2021-01-15T21:32:06.239-06:00","created_at":"2021-01-15T21:32:05.500-06:00","updated_at":"2021-01-15T21:55:21.883-06:00","identifier":"K","has_attachment":false,"round":2,"player1_votes":null,"player2_votes":null,"group_id":null,"attachment_count":null,"scheduled_time":null,"location":null,"underway_at":null,"optional":false,"rushb_id":null,"completed_at":"2021-01-15T21:55:21.929-06:00","suggested_play_order":7,"forfeited":null,"open_graph_image_file_name":null,"open_graph_image_content_type":null,"open_graph_image_file_size":null,"prerequisite_match_ids_csv":"","scores_csv":"3-2"}},{"match":{"id":224735644,"tournament_id":9325369,"state":"complete","player1_id":138064902,"player2_id":138064899,"player1_prereq_match_id":null,"player2_prereq_match_id":224735637,"player1_is_prereq_match_loser":false,"player2_is_prereq_match_loser":false,"winner_id":138064902,"loser_id":138064899,"started_at":"2021-01-15T22:06:04.117-06:00","created_at":"2021-01-15T21:32:05.504-06:00","updated_at":"2021-01-15T22:24:24.171-06:00","identifier":"L","has_attachment":false,"round":2,"player1_votes":null,"player2_votes":null,"group_id":null,"attachment_count":null,"scheduled_time":null,"location":null,"underway_at":null,"optional":false,"rushb_id":null,"completed_at":"2021-01-15T22:24:24.222-06:00","suggested_play_order":13,"forfeited":null,"open_graph_image_file_name":null,"open_graph_image_content_type":null,"open_graph_image_file_size":null,"prerequisite_match_ids_csv":"224735637","scores_csv":"3-0"}},{"match":{"id":224735645,"tournament_id":9325369,"state":"complete","player1_id":138064893,"player2_id":138065159,"player1_prereq_match_id":null,"player2_prereq_match_id":null,"player1_is_prereq_match_loser":false,"player2_is_prereq_match_loser":false,"winner_id":138064893,"loser_id":138065159,"started_at":"2021-01-15T21:32:06.253-06:00","created_at":"2021-01-15T21:32:05.509-06:00","updated_at":"2021-01-15T21:49:49.734-06:00","identifier":"M","has_attachment":false,"round":2,"player1_votes":null,"player2_votes":null,"group_id":null,"attachment_count":null,"scheduled_time":null,"location":null,"underway_at":null,"optional":false,"rushb_id":null,"completed_at":"2021-01-15T21:49:49.759-06:00","suggested_play_order":8,"forfeited":null,"open_graph_image_file_name":null,"open_graph_image_content_type":null,"open_graph_image_file_size":null,"prerequisite_match_ids_csv":"","scores_csv":"3-0"}},{"match":{"id":224735646,"tournament_id":9325369,"state":"complete","player1_id":138064901,"player2_id":138064900,"player1_prereq_match_id":224735638,"player2_prereq_match_id":224735639,"player1_is_prereq_match_loser":false,"player2_is_prereq_match_loser":false,"winner_id":138064901,"loser_id":138064900,"started_at":"2021-01-15T22:06:54.861-06:00","created_at":"2021-01-15T21:32:05.513-06:00","updated_at":"2021-01-15T22:19:16.802-06:00","identifier":"N","has_attachment":false,"round":3,"player1_votes":null,"player2_votes":null,"group_id":null,"attachment_count":null,"scheduled_time":null,"location":null,"underway_at":null,"optional":false,"rushb_id":null,"completed_at":"2021-01-15T22:19:16.837-06:00","suggested_play_order":23,"forfeited":null,"open_graph_image_file_name":null,"open_graph_image_content_type":null,"open_graph_image_file_size":null,"prerequisite_match_ids_csv":"224735638,224735639","scores_csv":"3-0"}},{"match":{"id":224735647,"tournament_id":9325369,"state":"complete","player1_id":138064897,"player2_id":138064887,"player1_prereq_match_id":224735640,"player2_prereq_match_id":224735641,"player1_is_prereq_match_loser":false,"player2_is_prereq_match_loser":false,"winner_id":138064887,"loser_id":138064897,"started_at":"2021-01-15T22:58:16.579-06:00","created_at":"2021-01-15T21:32:05.517-06:00","updated_at":"2021-01-15T23:11:14.449-06:00","identifier":"O","has_attachment":false,"round":3,"player1_votes":null,"player2_votes":null,"group_id":null,"attachment_count":null,"scheduled_time":null,"location":null,"underway_at":null,"optional":false,"rushb_id":null,"completed_at":"2021-01-15T23:11:14.488-06:00","suggested_play_order":24,"forfeited":false,"open_graph_image_file_name":null,"open_graph_image_content_type":null,"open_graph_image_file_size":null,"prerequisite_match_ids_csv":"224735640,224735641","scores_csv":"0-3"}},{"match":{"id":224735648,"tournament_id":9325369,"state":"complete","player1_id":138064898,"player2_id":138064890,"player1_prereq_match_id":224735642,"player2_prereq_match_id":224735643,"player1_is_prereq_match_loser":false,"player2_is_prereq_match_loser":false,"winner_id":138064898,"loser_id":138064890,"started_at":"2021-01-15T22:09:33.505-06:00","created_at":"2021-01-15T21:32:05.521-06:00","updated_at":"2021-01-15T22:24:18.657-06:00","identifier":"P","has_attachment":false,"round":3,"player1_votes":null,"player2_votes":null,"group_id":null,"attachment_count":null,"scheduled_time":null,"location":null,"underway_at":null,"optional":false,"rushb_id":null,"completed_at":"2021-01-15T22:24:18.681-06:00","suggested_play_order":25,"forfeited":null,"open_graph_image_file_name":null,"open_graph_image_content_type":null,"open_graph_image_file_size":null,"prerequisite_match_ids_csv":"224735642,224735643","scores_csv":"3-0"}},{"match":{"id":224735649,"tournament_id":9325369,"state":"complete","player1_id":138064902,"player2_id":138064893,"player1_prereq_match_id":224735644,"player2_prereq_match_id":224735645,"player1_is_prereq_match_loser":false,"player2_is_prereq_match_loser":false,"winner_id":138064893,"loser_id":138064902,"started_at":"2021-01-15T22:24:24.209-06:00","created_at":"2021-01-15T21:32:05.526-06:00","updated_at":"2021-01-15T22:51:53.570-06:00","identifier":"Q","has_attachment":false,"round":3,"player1_votes":null,"player2_votes":null,"group_id":null,"attachment_count":null,"scheduled_time":null,"location":null,"underway_at":null,"optional":false,"rushb_id":null,"completed_at":"2021-01-15T22:51:53.603-06:00","suggested_play_order":26,"forfeited":null,"open_graph_image_file_name":null,"open_graph_image_content_type":null,"open_graph_image_file_size":null,"prerequisite_match_ids_csv":"224735644,224735645","scores_csv":"2-3"}},{"match":{"id":224735650,"tournament_id":9325369,"state":"complete","player1_id":138064901,"player2_id":138064887,"player1_prereq_match_id":224735646,"player2_prereq_match_id":224735647,"player1_is_prereq_match_loser":false,"player2_is_prereq_match_loser":false,"winner_id":138064901,"loser_id":138064887,"started_at":"2021-01-15T23:11:14.479-06:00","created_at":"2021-01-15T21:32:05.530-06:00","updated_at":"2021-01-15T23:30:16.791-06:00","identifier":"R","has_attachment":false,"round":4,"player1_votes":null,"player2_votes":null,"group_id":null,"attachment_count":null,"scheduled_time":null,"location":null,"underway_at":null,"optional":false,"rushb_id":null,"completed_at":"2021-01-15T23:30:16.851-06:00","suggested_play_order":33,"forfeited":null,"open_graph_image_file_name":null,"open_graph_image_content_type":null,"open_graph_image_file_size":null,"prerequisite_match_ids_csv":"224735646,224735647","scores_csv":"3-0"}},{"match":{"id":224735651,"tournament_id":9325369,"state":"complete","player1_id":138064898,"player2_id":138064893,"player1_prereq_match_id":224735648,"player2_prereq_match_id":224735649,"player1_is_prereq_match_loser":false,"player2_is_prereq_match_loser":false,"winner_id":138064898,"loser_id":138064893,"started_at":"2021-01-15T22:51:53.596-06:00","created_at":"2021-01-15T21:32:05.534-06:00","updated_at":"2021-01-15T23:18:21.131-06:00","identifier":"S","has_attachment":false,"round":4,"player1_votes":null,"player2_votes":null,"group_id":null,"attachment_count":null,"scheduled_time":null,"location":null,"underway_at":null,"optional":false,"rushb_id":null,"completed_at":"2021-01-15T23:18:21.162-06:00","suggested_play_order":34,"forfeited":null,"open_graph_image_file_name":null,"open_graph_image_content_type":null,"open_graph_image_file_size":null,"prerequisite_match_ids_csv":"224735648,224735649","scores_csv":"3-2"}},{"match":{"id":224735652,"tournament_id":9325369,"state":"complete","player1_id":138064901,"player2_id":138064898,"player1_prereq_match_id":224735650,"player2_prereq_match_id":224735651,"player1_is_prereq_match_loser":false,"player2_is_prereq_match_loser":false,"winner_id":138064901,"loser_id":138064898,"started_at":"2021-01-15T23:30:16.839-06:00","created_at":"2021-01-15T21:32:05.538-06:00","updated_at":"2021-01-15T23:48:14.823-06:00","identifier":"T","has_attachment":false,"round":5,"player1_votes":null,"player2_votes":null,"group_id":null,"attachment_count":null,"scheduled_time":null,"location":null,"underway_at":null,"optional":false,"rushb_id":null,"completed_at":"2021-01-15T23:48:14.849-06:00","suggested_play_order":38,"forfeited":null,"open_graph_image_file_name":null,"open_graph_image_content_type":null,"open_graph_image_file_size":null,"prerequisite_match_ids_csv":"224735650,224735651","scores_csv":"3-0"}},{"match":{"id":224735653,"tournament_id":9325369,"state":"complete","player1_id":138065159,"player2_id":138064888,"player1_prereq_match_id":224735645,"player2_prereq_match_id":224735633,"player1_is_prereq_match_loser":true,"player2_is_prereq_match_loser":true,"winner_id":138065159,"loser_id":138064888,"started_at":"2021-01-15T21:54:22.271-06:00","created_at":"2021-01-15T21:32:05.542-06:00","updated_at":"2021-01-15T22:46:22.301-06:00","identifier":"W","has_attachment":false,"round":-1,"player1_votes":null,"player2_votes":null,"group_id":null,"attachment_count":null,"scheduled_time":null,"location":null,"underway_at":"2021-01-15T22:40:19.999-06:00","optional":false,"rushb_id":null,"completed_at":"2021-01-15T22:46:22.344-06:00","suggested_play_order":16,"forfeited":null,"open_graph_image_file_name":null,"open_graph_image_content_type":null,"open_graph_image_file_size":null,"prerequisite_match_ids_csv":"224735645,224735633","scores_csv":"3-0"}},{"match":{"id":224735654,"tournament_id":9325369,"state":"complete","player1_id":138064891,"player2_id":138064892,"player1_prereq_match_id":224735643,"player2_prereq_match_id":224735634,"player1_is_prereq_match_loser":true,"player2_is_prereq_match_loser":true,"winner_id":138064891,"loser_id":138064892,"started_at":"2021-01-15T21:55:21.920-06:00","created_at":"2021-01-15T21:32:05.546-06:00","updated_at":"2021-01-15T22:06:43.416-06:00","identifier":"X","has_attachment":false,"round":-1,"player1_votes":null,"player2_votes":null,"group_id":null,"attachment_count":null,"scheduled_time":null,"location":null,"underway_at":null,"optional":false,"rushb_id":null,"completed_at":"2021-01-15T22:06:43.431-06:00","suggested_play_order":15,"forfeited":null,"open_graph_image_file_name":null,"open_graph_image_content_type":null,"open_graph_image_file_size":null,"prerequisite_match_ids_csv":"224735643,224735634","scores_csv":"3-0"}},{"match":{"id":224735655,"tournament_id":9325369,"state":"complete","player1_id":138064889,"player2_id":138065160,"player1_prereq_match_id":224735642,"player2_prereq_match_id":224735635,"player1_is_prereq_match_loser":true,"player2_is_prereq_match_loser":true,"winner_id":138064889,"loser_id":138065160,"started_at":"2021-01-15T22:31:55.963-06:00","created_at":"2021-01-15T21:32:05.577-06:00","updated_at":"2021-01-15T22:33:31.043-06:00","identifier":"Y","has_attachment":false,"round":-1,"player1_votes":null,"player2_votes":null,"group_id":null,"attachment_count":null,"scheduled_time":null,"location":null,"underway_at":null,"optional":false,"rushb_id":null,"completed_at":"2021-01-15T22:33:31.066-06:00","suggested_play_order":18,"forfeited":null,"open_graph_image_file_name":null,"open_graph_image_content_type":null,"open_graph_image_file_size":null,"prerequisite_match_ids_csv":"224735642,224735635","scores_csv":"0--1"}},{"match":{"id":224735656,"tournament_id":9325369,"state":"complete","player1_id":138064896,"player2_id":138068477,"player1_prereq_match_id":224735641,"player2_prereq_match_id":224735636,"player1_is_prereq_match_loser":true,"player2_is_prereq_match_loser":true,"winner_id":138064896,"loser_id":138068477,"started_at":"2021-01-15T22:58:16.617-06:00","created_at":"2021-01-15T21:32:05.690-06:00","updated_at":"2021-01-15T23:18:29.081-06:00","identifier":"Z","has_attachment":false,"round":-1,"player1_votes":null,"player2_votes":null,"group_id":null,"attachment_count":null,"scheduled_time":null,"location":null,"underway_at":null,"optional":false,"rushb_id":null,"completed_at":"2021-01-15T23:18:29.106-06:00","suggested_play_order":17,"forfeited":false,"open_graph_image_file_name":null,"open_graph_image_content_type":null,"open_graph_image_file_size":null,"prerequisite_match_ids_csv":"224735641,224735636","scores_csv":"3-0"}},{"match":{"id":224735657,"tournament_id":9325369,"state":"complete","player1_id":138064886,"player2_id":138068562,"player1_prereq_match_id":224735639,"player2_prereq_match_id":224735637,"player1_is_prereq_match_loser":true,"player2_is_prereq_match_loser":true,"winner_id":138064886,"loser_id":138068562,"started_at":"2021-01-15T22:06:04.138-06:00","created_at":"2021-01-15T21:32:05.865-06:00","updated_at":"2021-01-15T22:27:59.730-06:00","identifier":"AA","has_attachment":false,"round":-1,"player1_votes":null,"player2_votes":null,"group_id":null,"attachment_count":null,"scheduled_time":null,"location":null,"underway_at":null,"optional":false,"rushb_id":null,"completed_at":"2021-01-15T22:27:59.773-06:00","suggested_play_order":14,"forfeited":null,"open_graph_image_file_name":null,"open_graph_image_content_type":null,"open_graph_image_file_size":null,"prerequisite_match_ids_csv":"224735639,224735637","scores_csv":"3-1"}},{"match":{"id":224735658,"tournament_id":9325369,"state":"complete","player1_id":138064899,"player2_id":138065159,"player1_prereq_match_id":224735644,"player2_prereq_match_id":224735653,"player1_is_prereq_match_loser":true,"player2_is_prereq_match_loser":false,"winner_id":138064899,"loser_id":138065159,"started_at":"2021-01-15T22:46:22.339-06:00","created_at":"2021-01-15T21:32:05.870-06:00","updated_at":"2021-01-15T23:11:24.671-06:00","identifier":"AB","has_attachment":false,"round":-2,"player1_votes":null,"player2_votes":null,"group_id":null,"attachment_count":null,"scheduled_time":null,"location":null,"underway_at":null,"optional":false,"rushb_id":null,"completed_at":"2021-01-15T23:11:24.705-06:00","suggested_play_order":20,"forfeited":null,"open_graph_image_file_name":null,"open_graph_image_content_type":null,"open_graph_image_file_size":null,"prerequisite_match_ids_csv":"224735644,224735653","scores_csv":"0--1"}},{"match":{"id":224735659,"tournament_id":9325369,"state":"complete","player1_id":138064891,"player2_id":138064889,"player1_prereq_match_id":224735654,"player2_prereq_match_id":224735655,"player1_is_prereq_match_loser":false,"player2_is_prereq_match_loser":false,"winner_id":138064889,"loser_id":138064891,"started_at":"2021-01-15T22:33:31.060-06:00","created_at":"2021-01-15T21:32:05.875-06:00","updated_at":"2021-01-15T22:59:47.743-06:00","identifier":"AC","has_attachment":false,"round":-2,"player1_votes":null,"player2_votes":null,"group_id":null,"attachment_count":null,"scheduled_time":null,"location":null,"underway_at":null,"optional":false,"rushb_id":null,"completed_at":"2021-01-15T22:59:47.767-06:00","suggested_play_order":22,"forfeited":null,"open_graph_image_file_name":null,"open_graph_image_content_type":null,"open_graph_image_file_size":null,"prerequisite_match_ids_csv":"224735654,224735655","scores_csv":"2-3"}},{"match":{"id":224735660,"tournament_id":9325369,"state":"complete","player1_id":138064895,"player2_id":138064896,"player1_prereq_match_id":224735640,"player2_prereq_match_id":224735656,"player1_is_prereq_match_loser":true,"player2_is_prereq_match_loser":false,"winner_id":138064896,"loser_id":138064895,"started_at":"2021-01-15T23:18:29.099-06:00","created_at":"2021-01-15T21:32:05.879-06:00","updated_at":"2021-01-15T23:26:18.254-06:00","identifier":"AD","has_attachment":false,"round":-2,"player1_votes":null,"player2_votes":null,"group_id":null,"attachment_count":null,"scheduled_time":null,"location":null,"underway_at":null,"optional":false,"rushb_id":null,"completed_at":"2021-01-15T23:26:18.275-06:00","suggested_play_order":21,"forfeited":null,"open_graph_image_file_name":null,"open_graph_image_content_type":null,"open_graph_image_file_size":null,"prerequisite_match_ids_csv":"224735640,224735656","scores_csv":"0-3"}},{"match":{"id":224735661,"tournament_id":9325369,"state":"complete","player1_id":138064894,"player2_id":138064886,"player1_prereq_match_id":224735638,"player2_prereq_match_id":224735657,"player1_is_prereq_match_loser":true,"player2_is_prereq_match_loser":false,"winner_id":138064886,"loser_id":138064894,"started_at":"2021-01-15T22:27:59.764-06:00","created_at":"2021-01-15T21:32:05.883-06:00","updated_at":"2021-01-15T22:59:34.895-06:00","identifier":"AE","has_attachment":false,"round":-2,"player1_votes":null,"player2_votes":null,"group_id":null,"attachment_count":null,"scheduled_time":null,"location":null,"underway_at":null,"optional":false,"rushb_id":null,"completed_at":"2021-01-15T22:59:34.938-06:00","suggested_play_order":19,"forfeited":null,"open_graph_image_file_name":null,"open_graph_image_content_type":null,"open_graph_image_file_size":null,"prerequisite_match_ids_csv":"224735638,224735657","scores_csv":"1-3"}},{"match":{"id":224735662,"tournament_id":9325369,"state":"complete","player1_id":138064897,"player2_id":138064899,"player1_prereq_match_id":224735647,"player2_prereq_match_id":224735658,"player1_is_prereq_match_loser":true,"player2_is_prereq_match_loser":false,"winner_id":138064899,"loser_id":138064897,"started_at":"2021-01-15T23:11:24.697-06:00","created_at":"2021-01-15T21:32:05.887-06:00","updated_at":"2021-01-15T23:12:41.247-06:00","identifier":"AF","has_attachment":false,"round":-3,"player1_votes":null,"player2_votes":null,"group_id":null,"attachment_count":null,"scheduled_time":null,"location":null,"underway_at":null,"optional":false,"rushb_id":null,"completed_at":"2021-01-15T23:12:41.295-06:00","suggested_play_order":28,"forfeited":null,"open_graph_image_file_name":null,"open_graph_image_content_type":null,"open_graph_image_file_size":null,"prerequisite_match_ids_csv":"224735647,224735658","scores_csv":"-1-0"}},{"match":{"id":224735663,"tournament_id":9325369,"state":"complete","player1_id":138064900,"player2_id":138064889,"player1_prereq_match_id":224735646,"player2_prereq_match_id":224735659,"player1_is_prereq_match_loser":true,"player2_is_prereq_match_loser":false,"winner_id":138064900,"loser_id":138064889,"started_at":"2021-01-15T22:59:47.760-06:00","created_at":"2021-01-15T21:32:05.891-06:00","updated_at":"2021-01-15T23:13:23.608-06:00","identifier":"AG","has_attachment":false,"round":-3,"player1_votes":null,"player2_votes":null,"group_id":null,"attachment_count":null,"scheduled_time":null,"location":null,"underway_at":null,"optional":false,"rushb_id":null,"completed_at":"2021-01-15T23:13:23.627-06:00","suggested_play_order":27,"forfeited":null,"open_graph_image_file_name":null,"open_graph_image_content_type":null,"open_graph_image_file_size":null,"prerequisite_match_ids_csv":"224735646,224735659","scores_csv":"3-0"}},{"match":{"id":224735664,"tournament_id":9325369,"state":"complete","player1_id":138064902,"player2_id":138064896,"player1_prereq_match_id":224735649,"player2_prereq_match_id":224735660,"player1_is_prereq_match_loser":true,"player2_is_prereq_match_loser":false,"winner_id":138064902,"loser_id":138064896,"started_at":"2021-01-15T23:26:18.269-06:00","created_at":"2021-01-15T21:32:05.895-06:00","updated_at":"2021-01-15T23:45:36.010-06:00","identifier":"AH","has_attachment":false,"round":-3,"player1_votes":null,"player2_votes":null,"group_id":null,"attachment_count":null,"scheduled_time":null,"location":null,"underway_at":null,"optional":false,"rushb_id":null,"completed_at":"2021-01-15T23:45:36.031-06:00","suggested_play_order":30,"forfeited":null,"open_graph_image_file_name":null,"open_graph_image_content_type":null,"open_graph_image_file_size":null,"prerequisite_match_ids_csv":"224735649,224735660","scores_csv":"3-1"}},{"match":{"id":224735665,"tournament_id":9325369,"state":"complete","player1_id":138064890,"player2_id":138064886,"player1_prereq_match_id":224735648,"player2_prereq_match_id":224735661,"player1_is_prereq_match_loser":true,"player2_is_prereq_match_loser":false,"winner_id":138064890,"loser_id":138064886,"started_at":"2021-01-15T22:59:34.932-06:00","created_at":"2021-01-15T21:32:05.899-06:00","updated_at":"2021-01-15T23:11:35.028-06:00","identifier":"AI","has_attachment":false,"round":-3,"player1_votes":null,"player2_votes":null,"group_id":null,"attachment_count":null,"scheduled_time":null,"location":null,"underway_at":null,"optional":false,"rushb_id":null,"completed_at":"2021-01-15T23:11:35.050-06:00","suggested_play_order":29,"forfeited":null,"open_graph_image_file_name":null,"open_graph_image_content_type":null,"open_graph_image_file_size":null,"prerequisite_match_ids_csv":"224735648,224735661","scores_csv":"3-1"}},{"match":{"id":224735666,"tournament_id":9325369,"state":"complete","player1_id":138064899,"player2_id":138064900,"player1_prereq_match_id":224735662,"player2_prereq_match_id":224735663,"player1_is_prereq_match_loser":false,"player2_is_prereq_match_loser":false,"winner_id":138064900,"loser_id":138064899,"started_at":"2021-01-15T23:13:23.622-06:00","created_at":"2021-01-15T21:32:05.903-06:00","updated_at":"2021-01-15T23:28:23.005-06:00","identifier":"AJ","has_attachment":false,"round":-4,"player1_votes":null,"player2_votes":null,"group_id":null,"attachment_count":null,"scheduled_time":null,"location":null,"underway_at":null,"optional":false,"rushb_id":null,"completed_at":"2021-01-15T23:28:23.028-06:00","suggested_play_order":31,"forfeited":null,"open_graph_image_file_name":null,"open_graph_image_content_type":null,"open_graph_image_file_size":null,"prerequisite_match_ids_csv":"224735662,224735663","scores_csv":"0-3"}},{"match":{"id":224735667,"tournament_id":9325369,"state":"complete","player1_id":138064902,"player2_id":138064890,"player1_prereq_match_id":224735664,"player2_prereq_match_id":224735665,"player1_is_prereq_match_loser":false,"player2_is_prereq_match_loser":false,"winner_id":138064902,"loser_id":138064890,"started_at":"2021-01-15T23:45:36.024-06:00","created_at":"2021-01-15T21:32:05.907-06:00","updated_at":"2021-01-16T00:10:10.642-06:00","identifier":"AK","has_attachment":false,"round":-4,"player1_votes":null,"player2_votes":null,"group_id":null,"attachment_count":null,"scheduled_time":null,"location":null,"underway_at":null,"optional":false,"rushb_id":null,"completed_at":"2021-01-16T00:10:10.670-06:00","suggested_play_order":32,"forfeited":false,"open_graph_image_file_name":null,"open_graph_image_content_type":null,"open_graph_image_file_size":null,"prerequisite_match_ids_csv":"224735664,224735665","scores_csv":"3-1"}},{"match":{"id":224735668,"tournament_id":9325369,"state":"complete","player1_id":138064893,"player2_id":138064900,"player1_prereq_match_id":224735651,"player2_prereq_match_id":224735666,"player1_is_prereq_match_loser":true,"player2_is_prereq_match_loser":false,"winner_id":138064893,"loser_id":138064900,"started_at":"2021-01-15T23:28:23.021-06:00","created_at":"2021-01-15T21:32:05.912-06:00","updated_at":"2021-01-15T23:50:37.239-06:00","identifier":"AL","has_attachment":false,"round":-5,"player1_votes":null,"player2_votes":null,"group_id":null,"attachment_count":null,"scheduled_time":null,"location":null,"underway_at":null,"optional":false,"rushb_id":null,"completed_at":"2021-01-15T23:50:37.254-06:00","suggested_play_order":36,"forfeited":null,"open_graph_image_file_name":null,"open_graph_image_content_type":null,"open_graph_image_file_size":null,"prerequisite_match_ids_csv":"224735651,224735666","scores_csv":"3-2"}},{"match":{"id":224735669,"tournament_id":9325369,"state":"complete","player1_id":138064887,"player2_id":138064902,"player1_prereq_match_id":224735650,"player2_prereq_match_id":224735667,"player1_is_prereq_match_loser":true,"player2_is_prereq_match_loser":false,"winner_id":138064902,"loser_id":138064887,"started_at":"2021-01-16T00:10:10.663-06:00","created_at":"2021-01-15T21:32:05.915-06:00","updated_at":"2021-01-16T00:30:04.170-06:00","identifier":"AM","has_attachment":false,"round":-5,"player1_votes":null,"player2_votes":null,"group_id":null,"attachment_count":null,"scheduled_time":null,"location":null,"underway_at":null,"optional":false,"rushb_id":null,"completed_at":"2021-01-16T00:30:04.202-06:00","suggested_play_order":35,"forfeited":false,"open_graph_image_file_name":null,"open_graph_image_content_type":null,"open_graph_image_file_size":null,"prerequisite_match_ids_csv":"224735650,224735667","scores_csv":"1-3"}},{"match":{"id":224735670,"tournament_id":9325369,"state":"complete","player1_id":138064893,"player2_id":138064902,"player1_prereq_match_id":224735668,"player2_prereq_match_id":224735669,"player1_is_prereq_match_loser":false,"player2_is_prereq_match_loser":false,"winner_id":138064902,"loser_id":138064893,"started_at":"2021-01-16T00:30:04.195-06:00","created_at":"2021-01-15T21:32:05.920-06:00","updated_at":"2021-01-16T00:50:17.947-06:00","identifier":"AN","has_attachment":false,"round":-6,"player1_votes":null,"player2_votes":null,"group_id":null,"attachment_count":null,"scheduled_time":null,"location":null,"underway_at":null,"optional":false,"rushb_id":null,"completed_at":"2021-01-16T00:50:17.967-06:00","suggested_play_order":37,"forfeited":null,"open_graph_image_file_name":null,"open_graph_image_content_type":null,"open_graph_image_file_size":null,"prerequisite_match_ids_csv":"224735668,224735669","scores_csv":"1-3"}},{"match":{"id":224735671,"tournament_id":9325369,"state":"complete","player1_id":138064898,"player2_id":138064902,"player1_prereq_match_id":224735652,"player2_prereq_match_id":224735670,"player1_is_prereq_match_loser":true,"player2_is_prereq_match_loser":false,"winner_id":138064902,"loser_id":138064898,"started_at":"2021-01-16T00:50:17.962-06:00","created_at":"2021-01-15T21:32:05.924-06:00","updated_at":"2021-01-16T01:03:25.692-06:00","identifier":"AO","has_attachment":false,"round":-7,"player1_votes":null,"player2_votes":null,"group_id":null,"attachment_count":null,"scheduled_time":null,"location":null,"underway_at":null,"optional":false,"rushb_id":null,"completed_at":"2021-01-16T01:03:25.716-06:00","suggested_play_order":39,"forfeited":null,"open_graph_image_file_name":null,"open_graph_image_content_type":null,"open_graph_image_file_size":null,"prerequisite_match_ids_csv":"224735652,224735670","scores_csv":"-1-0"}},{"match":{"id":224735672,"tournament_id":9325369,"state":"complete","player1_id":138064901,"player2_id":138064902,"player1_prereq_match_id":224735652,"player2_prereq_match_id":224735671,"player1_is_prereq_match_loser":false,"player2_is_prereq_match_loser":false,"winner_id":138064902,"loser_id":138064901,"started_at":"2021-01-16T01:03:25.711-06:00","created_at":"2021-01-15T21:32:05.928-06:00","updated_at":"2021-01-16T01:30:51.394-06:00","identifier":"U","has_attachment":false,"round":6,"player1_votes":null,"player2_votes":null,"group_id":null,"attachment_count":null,"scheduled_time":null,"location":null,"underway_at":null,"optional":false,"rushb_id":null,"completed_at":"2021-01-16T01:30:51.428-06:00","suggested_play_order":40,"forfeited":null,"open_graph_image_file_name":null,"open_graph_image_content_type":null,"open_graph_image_file_size":null,"prerequisite_match_ids_csv":"224735652,224735671","scores_csv":"2-3"}},{"match":{"id":224735673,"tournament_id":9325369,"state":"complete","player1_id":138064902,"player2_id":138064901,"player1_prereq_match_id":224735672,"player2_prereq_match_id":224735672,"player1_is_prereq_match_loser":false,"player2_is_prereq_match_loser":true,"winner_id":138064901,"loser_id":138064902,"started_at":"2021-01-16T01:30:51.418-06:00","created_at":"2021-01-15T21:32:05.932-06:00","updated_at":"2021-01-16T01:49:04.131-06:00","identifier":"V","has_attachment":false,"round":6,"player1_votes":null,"player2_votes":null,"group_id":null,"attachment_count":null,"scheduled_time":null,"location":null,"underway_at":null,"optional":false,"rushb_id":null,"completed_at":"2021-01-16T01:49:04.152-06:00","suggested_play_order":41,"forfeited":null,"open_graph_image_file_name":null,"open_graph_image_content_type":null,"open_graph_image_file_size":null,"prerequisite_match_ids_csv":"224735672","scores_csv":"1-3"}}]