[{"participant":{"id":154970831,"tournament_id":10279250,"name":"Traplord [TRAP#719]","seed":1,"active":true,"created_at":"2021-09-17T18:53:35.039-07:00","updated_at":"2021-09-17T19:02:45.364-07:00","invite_email":null,"final_rank":5,"misc":null,"icon":null,"on_waiting_list":false,"invitation_id":null,"group_id":null,"checked_in_at":null,"ranked_member_id":null,"custom_field_response":null,"clinch":null,"integration_uids":null,"challonge_username":null,"challonge_email_address_verified":null,"removable":false,"participatable_or_invitation_attached":false,"confirm_remove":true,"invitation_pending":false,"display_name_with_invitation_email_address":"Traplord [TRAP#719]","email_hash":null,"username":null,"display_name":"Traplord [TRAP#719]","attached_participatable_portrait_url":null,"can_check_in":false,"checked_in":false,"reactivatable":false,"check_in_open":false,"group_player_ids":[],"has_irrelevant_seed":false}},{"participant":{"id":154973202,"tournament_id":10279250,"name":"spacepigeon [SF#0]","seed":2,"active":true,"created_at":"2021-09-17T19:47:09.382-07:00","updated_at":"2021-09-17T19:47:34.232-07:00","invite_email":null,"final_rank":3,"misc":null,"icon":null,"on_waiting_list":false,"invitation_id":null,"group_id":null,"checked_in_at":null,"ranked_member_id":null,"custom_field_response":null,"clinch":null,"integration_uids":null,"challonge_username":null,"challonge_email_address_verified":null,"removable":false,"participatable_or_invitation_attached":false,"confirm_remove":true,"invitation_pending":false,"display_name_with_invitation_email_address":"spacepigeon [SF#0]","email_hash":null,"username":null,"display_name":"spacepigeon [SF#0]","attached_participatable_portrait_url":null,"can_check_in":false,"checked_in":false,"reactivatable":false,"check_in_open":false,"group_player_ids":[],"has_irrelevant_seed":false}},{"participant":{"id":154968951,"tournament_id":10279250,"name":"Supercuak [CUAK#787]","seed":3,"active":true,"created_at":"2021-09-17T18:13:24.086-07:00","updated_at":"2021-09-17T18:15:51.888-07:00","invite_email":null,"final_rank":2,"misc":null,"icon":null,"on_waiting_list":false,"invitation_id":null,"group_id":null,"checked_in_at":null,"ranked_member_id":null,"custom_field_response":null,"clinch":null,"integration_uids":null,"challonge_username":null,"challonge_email_address_verified":null,"removable":false,"participatable_or_invitation_attached":false,"confirm_remove":true,"invitation_pending":false,"display_name_with_invitation_email_address":"Supercuak [CUAK#787]","email_hash":null,"username":null,"display_name":"Supercuak [CUAK#787]","attached_participatable_portrait_url":null,"can_check_in":false,"checked_in":false,"reactivatable":false,"check_in_open":false,"group_player_ids":[],"has_irrelevant_seed":false}},{"participant":{"id":154968958,"tournament_id":10279250,"name":"Ford$ [FORD#938]","seed":4,"active":true,"created_at":"2021-09-17T18:13:24.345-07:00","updated_at":"2021-09-17T18:14:54.961-07:00","invite_email":null,"final_rank":1,"misc":null,"icon":null,"on_waiting_list":false,"invitation_id":null,"group_id":null,"checked_in_at":null,"ranked_member_id":null,"custom_field_response":null,"clinch":null,"integration_uids":null,"challonge_username":null,"challonge_email_address_verified":null,"removable":false,"participatable_or_invitation_attached":false,"confirm_remove":true,"invitation_pending":false,"display_name_with_invitation_email_address":"Ford$ [FORD#938]","email_hash":null,"username":null,"display_name":"Ford$ [FORD#938]","attached_participatable_portrait_url":null,"can_check_in":false,"checked_in":false,"reactivatable":false,"check_in_open":false,"group_player_ids":[],"has_irrelevant_seed":false}},{"participant":{"id":154971428,"tournament_id":10279250,"name":"Iron [IRON#446]","seed":5,"active":true,"created_at":"2021-09-17T19:07:39.357-07:00","updated_at":"2021-09-17T19:08:03.688-07:00","invite_email":null,"final_rank":9,"misc":null,"icon":null,"on_waiting_list":false,"invitation_id":null,"group_id":null,"checked_in_at":null,"ranked_member_id":null,"custom_field_response":null,"clinch":null,"integration_uids":null,"challonge_username":null,"challonge_email_address_verified":null,"removable":false,"participatable_or_invitation_attached":false,"confirm_remove":true,"invitation_pending":false,"display_name_with_invitation_email_address":"Iron [IRON#446]","email_hash":null,"username":null,"display_name":"Iron [IRON#446]","attached_participatable_portrait_url":null,"can_check_in":false,"checked_in":false,"reactivatable":false,"check_in_open":false,"group_player_ids":[],"has_irrelevant_seed":false}},{"participant":{"id":154968956,"tournament_id":10279250,"name":"Askromas [ASKR#514]","seed":6,"active":true,"created_at":"2021-09-17T18:13:24.286-07:00","updated_at":"2021-09-17T18:14:14.836-07:00","invite_email":null,"final_rank":5,"misc":null,"icon":null,"on_waiting_list":false,"invitation_id":null,"group_id":null,"checked_in_at":null,"ranked_member_id":null,"custom_field_response":null,"clinch":null,"integration_uids":null,"challonge_username":null,"challonge_email_address_verified":null,"removable":false,"participatable_or_invitation_attached":false,"confirm_remove":true,"invitation_pending":false,"display_name_with_invitation_email_address":"Askromas [ASKR#514]","email_hash":null,"username":null,"display_name":"Askromas [ASKR#514]","attached_participatable_portrait_url":null,"can_check_in":false,"checked_in":false,"reactivatable":false,"check_in_open":false,"group_player_ids":[],"has_irrelevant_seed":false}},{"participant":{"id":154968947,"tournament_id":10279250,"name":"Cow [COW#955]","seed":7,"active":true,"created_at":"2021-09-17T18:13:23.948-07:00","updated_at":"2021-09-17T19:03:18.588-07:00","invite_email":null,"final_rank":7,"misc":null,"icon":null,"on_waiting_list":false,"invitation_id":null,"group_id":null,"checked_in_at":null,"ranked_member_id":null,"custom_field_response":null,"clinch":null,"integration_uids":null,"challonge_username":null,"challonge_email_address_verified":null,"removable":false,"participatable_or_invitation_attached":false,"confirm_remove":true,"invitation_pending":false,"display_name_with_invitation_email_address":"Cow [COW#955]","email_hash":null,"username":null,"display_name":"Cow [COW#955]","attached_participatable_portrait_url":null,"can_check_in":false,"checked_in":false,"reactivatable":false,"check_in_open":false,"group_player_ids":[],"has_irrelevant_seed":false}},{"participant":{"id":154971807,"tournament_id":10279250,"name":"RATS [RATS#141]","seed":8,"active":true,"created_at":"2021-09-17T19:11:53.913-07:00","updated_at":"2021-09-17T19:12:30.314-07:00","invite_email":null,"final_rank":4,"misc":null,"icon":null,"on_waiting_list":false,"invitation_id":null,"group_id":null,"checked_in_at":null,"ranked_member_id":null,"custom_field_response":null,"clinch":null,"integration_uids":null,"challonge_username":null,"challonge_email_address_verified":null,"removable":false,"participatable_or_invitation_attached":false,"confirm_remove":true,"invitation_pending":false,"display_name_with_invitation_email_address":"RATS [RATS#141]","email_hash":null,"username":null,"display_name":"RATS [RATS#141]","attached_participatable_portrait_url":null,"can_check_in":false,"checked_in":false,"reactivatable":false,"check_in_open":false,"group_player_ids":[],"has_irrelevant_seed":false}},{"participant":{"id":154968957,"tournament_id":10279250,"name":"mmunder [MM#291]","seed":9,"active":true,"created_at":"2021-09-17T18:13:24.316-07:00","updated_at":"2021-09-17T18:14:00.461-07:00","invite_email":null,"final_rank":13,"misc":null,"icon":null,"on_waiting_list":false,"invitation_id":null,"group_id":null,"checked_in_at":null,"ranked_member_id":null,"custom_field_response":null,"clinch":null,"integration_uids":null,"challonge_username":null,"challonge_email_address_verified":null,"removable":false,"participatable_or_invitation_attached":false,"confirm_remove":true,"invitation_pending":false,"display_name_with_invitation_email_address":"mmunder [MM#291]","email_hash":null,"username":null,"display_name":"mmunder [MM#291]","attached_participatable_portrait_url":null,"can_check_in":false,"checked_in":false,"reactivatable":false,"check_in_open":false,"group_player_ids":[],"has_irrelevant_seed":false}},{"participant":{"id":154971230,"tournament_id":10279250,"name":"Haze [SMAS#888]","seed":10,"active":true,"created_at":"2021-09-17T19:02:54.763-07:00","updated_at":"2021-09-17T19:03:16.810-07:00","invite_email":null,"final_rank":9,"misc":null,"icon":null,"on_waiting_list":false,"invitation_id":null,"group_id":null,"checked_in_at":null,"ranked_member_id":null,"custom_field_response":null,"clinch":null,"integration_uids":null,"challonge_username":null,"challonge_email_address_verified":null,"removable":false,"participatable_or_invitation_attached":false,"confirm_remove":true,"invitation_pending":false,"display_name_with_invitation_email_address":"Haze [SMAS#888]","email_hash":null,"username":null,"display_name":"Haze [SMAS#888]","attached_participatable_portrait_url":null,"can_check_in":false,"checked_in":false,"reactivatable":false,"check_in_open":false,"group_player_ids":[],"has_irrelevant_seed":false}},{"participant":{"id":154968952,"tournament_id":10279250,"name":"Sunshine [SUNS#683]","seed":11,"active":true,"created_at":"2021-09-17T18:13:24.120-07:00","updated_at":"2021-09-17T18:14:31.167-07:00","invite_email":null,"final_rank":7,"misc":null,"icon":null,"on_waiting_list":false,"invitation_id":null,"group_id":null,"checked_in_at":null,"ranked_member_id":null,"custom_field_response":null,"clinch":null,"integration_uids":null,"challonge_username":null,"challonge_email_address_verified":null,"removable":false,"participatable_or_invitation_attached":false,"confirm_remove":true,"invitation_pending":false,"display_name_with_invitation_email_address":"Sunshine [SUNS#683]","email_hash":null,"username":null,"display_name":"Sunshine [SUNS#683]","attached_participatable_portrait_url":null,"can_check_in":false,"checked_in":false,"reactivatable":false,"check_in_open":false,"group_player_ids":[],"has_irrelevant_seed":false}},{"participant":{"id":154975328,"tournament_id":10279250,"name":"Mucho Man Randy Passion [MMRP#834]","seed":12,"active":true,"created_at":"2021-09-17T20:25:51.122-07:00","updated_at":"2021-09-17T20:26:15.860-07:00","invite_email":null,"final_rank":9,"misc":null,"icon":null,"on_waiting_list":false,"invitation_id":null,"group_id":null,"checked_in_at":null,"ranked_member_id":null,"custom_field_response":null,"clinch":null,"integration_uids":null,"challonge_username":null,"challonge_email_address_verified":null,"removable":false,"participatable_or_invitation_attached":false,"confirm_remove":true,"invitation_pending":false,"display_name_with_invitation_email_address":"Mucho Man Randy Passion [MMRP#834]","email_hash":null,"username":null,"display_name":"Mucho Man Randy Passion [MMRP#834]","attached_participatable_portrait_url":null,"can_check_in":false,"checked_in":false,"reactivatable":false,"check_in_open":false,"group_player_ids":[],"has_irrelevant_seed":false}},{"participant":{"id":154968950,"tournament_id":10279250,"name":"Advanced Placement [AP#557]","seed":13,"active":true,"created_at":"2021-09-17T18:13:24.046-07:00","updated_at":"2021-09-17T18:14:49.428-07:00","invite_email":null,"final_rank":13,"misc":null,"icon":null,"on_waiting_list":false,"invitation_id":null,"group_id":null,"checked_in_at":null,"ranked_member_id":null,"custom_field_response":null,"clinch":null,"integration_uids":null,"challonge_username":null,"challonge_email_address_verified":null,"removable":false,"participatable_or_invitation_attached":false,"confirm_remove":true,"invitation_pending":false,"display_name_with_invitation_email_address":"Advanced Placement [AP#557]","email_hash":null,"username":null,"display_name":"Advanced Placement [AP#557]","attached_participatable_portrait_url":null,"can_check_in":false,"checked_in":false,"reactivatable":false,"check_in_open":false,"group_player_ids":[],"has_irrelevant_seed":false}},{"participant":{"id":154968953,"tournament_id":10279250,"name":"Potion [POT#420]","seed":14,"active":true,"created_at":"2021-09-17T18:13:24.170-07:00","updated_at":"2021-09-17T18:14:21.003-07:00","invite_email":null,"final_rank":13,"misc":null,"icon":null,"on_waiting_list":false,"invitation_id":null,"group_id":null,"checked_in_at":null,"ranked_member_id":null,"custom_field_response":null,"clinch":null,"integration_uids":null,"challonge_username":null,"challonge_email_address_verified":null,"removable":false,"participatable_or_invitation_attached":false,"confirm_remove":true,"invitation_pending":false,"display_name_with_invitation_email_address":"Potion [POT#420]","email_hash":null,"username":null,"display_name":"Potion [POT#420]","attached_participatable_portrait_url":null,"can_check_in":false,"checked_in":false,"reactivatable":false,"check_in_open":false,"group_player_ids":[],"has_irrelevant_seed":false}},{"participant":{"id":154968944,"tournament_id":10279250,"name":"Mofat [MOFA#575]","seed":15,"active":true,"created_at":"2021-09-17T18:13:23.845-07:00","updated_at":"2021-09-17T18:14:34.630-07:00","invite_email":null,"final_rank":17,"misc":null,"icon":null,"on_waiting_list":false,"invitation_id":null,"group_id":null,"checked_in_at":null,"ranked_member_id":null,"custom_field_response":null,"clinch":null,"integration_uids":null,"challonge_username":null,"challonge_email_address_verified":null,"removable":false,"participatable_or_invitation_attached":false,"confirm_remove":true,"invitation_pending":false,"display_name_with_invitation_email_address":"Mofat [MOFA#575]","email_hash":null,"username":null,"display_name":"Mofat [MOFA#575]","attached_participatable_portrait_url":null,"can_check_in":false,"checked_in":false,"reactivatable":false,"check_in_open":false,"group_player_ids":[],"has_irrelevant_seed":false}},{"participant":{"id":154972517,"tournament_id":10279250,"name":"Equi [EQUI#0]","seed":16,"active":true,"created_at":"2021-09-17T19:31:57.868-07:00","updated_at":"2021-09-17T19:34:01.534-07:00","invite_email":null,"final_rank":9,"misc":null,"icon":null,"on_waiting_list":false,"invitation_id":null,"group_id":null,"checked_in_at":null,"ranked_member_id":null,"custom_field_response":null,"clinch":null,"integration_uids":null,"challonge_username":null,"challonge_email_address_verified":null,"removable":false,"participatable_or_invitation_attached":false,"confirm_remove":true,"invitation_pending":false,"display_name_with_invitation_email_address":"Equi [EQUI#0]","email_hash":null,"username":null,"display_name":"Equi [EQUI#0]","attached_participatable_portrait_url":null,"can_check_in":false,"checked_in":false,"reactivatable":false,"check_in_open":false,"group_player_ids":[],"has_irrelevant_seed":false}},{"participant":{"id":154968955,"tournament_id":10279250,"name":"swan [SWAN#349]","seed":17,"active":true,"created_at":"2021-09-17T18:13:24.243-07:00","updated_at":"2021-09-17T18:14:17.839-07:00","invite_email":null,"final_rank":17,"misc":null,"icon":null,"on_waiting_list":false,"invitation_id":null,"group_id":null,"checked_in_at":null,"ranked_member_id":null,"custom_field_response":null,"clinch":null,"integration_uids":null,"challonge_username":null,"challonge_email_address_verified":null,"removable":false,"participatable_or_invitation_attached":false,"confirm_remove":true,"invitation_pending":false,"display_name_with_invitation_email_address":"swan [SWAN#349]","email_hash":null,"username":null,"display_name":"swan [SWAN#349]","attached_participatable_portrait_url":null,"can_check_in":false,"checked_in":false,"reactivatable":false,"check_in_open":false,"group_player_ids":[],"has_irrelevant_seed":false}},{"participant":{"id":154968945,"tournament_id":10279250,"name":"CrystalS1n [SIN#618]","seed":18,"active":true,"created_at":"2021-09-17T18:13:23.890-07:00","updated_at":"2021-09-17T19:16:24.570-07:00","invite_email":null,"final_rank":17,"misc":null,"icon":null,"on_waiting_list":false,"invitation_id":null,"group_id":null,"checked_in_at":null,"ranked_member_id":null,"custom_field_response":null,"clinch":null,"integration_uids":null,"challonge_username":null,"challonge_email_address_verified":null,"removable":false,"participatable_or_invitation_attached":false,"confirm_remove":true,"invitation_pending":false,"display_name_with_invitation_email_address":"CrystalS1n [SIN#618]","email_hash":null,"username":null,"display_name":"CrystalS1n [SIN#618]","attached_participatable_portrait_url":null,"can_check_in":false,"checked_in":false,"reactivatable":false,"check_in_open":false,"group_player_ids":[],"has_irrelevant_seed":false}},{"participant":{"id":154970830,"tournament_id":10279250,"name":"CaptnGalaxy [CAPT#323]","seed":19,"active":true,"created_at":"2021-09-17T18:53:35.006-07:00","updated_at":"2021-09-17T19:06:04.064-07:00","invite_email":null,"final_rank":17,"misc":null,"icon":null,"on_waiting_list":false,"invitation_id":null,"group_id":null,"checked_in_at":null,"ranked_member_id":null,"custom_field_response":null,"clinch":null,"integration_uids":null,"challonge_username":null,"challonge_email_address_verified":null,"removable":false,"participatable_or_invitation_attached":false,"confirm_remove":true,"invitation_pending":false,"display_name_with_invitation_email_address":"CaptnGalaxy [CAPT#323]","email_hash":null,"username":null,"display_name":"CaptnGalaxy [CAPT#323]","attached_participatable_portrait_url":null,"can_check_in":false,"checked_in":false,"reactivatable":false,"check_in_open":false,"group_player_ids":[],"has_irrelevant_seed":false}},{"participant":{"id":154975327,"tournament_id":10279250,"name":"glazed [LEGY#920]","seed":20,"active":true,"created_at":"2021-09-17T20:25:51.058-07:00","updated_at":"2021-09-17T20:26:00.457-07:00","invite_email":null,"final_rank":17,"misc":null,"icon":null,"on_waiting_list":false,"invitation_id":null,"group_id":null,"checked_in_at":null,"ranked_member_id":null,"custom_field_response":null,"clinch":null,"integration_uids":null,"challonge_username":null,"challonge_email_address_verified":null,"removable":false,"participatable_or_invitation_attached":false,"confirm_remove":true,"invitation_pending":false,"display_name_with_invitation_email_address":"glazed [LEGY#920]","email_hash":null,"username":null,"display_name":"glazed [LEGY#920]","attached_participatable_portrait_url":null,"can_check_in":false,"checked_in":false,"reactivatable":false,"check_in_open":false,"group_player_ids":[],"has_irrelevant_seed":false}},{"participant":{"id":154968954,"tournament_id":10279250,"name":"Artie [RT#0]","seed":21,"active":true,"created_at":"2021-09-17T18:13:24.209-07:00","updated_at":"2021-09-17T18:13:24.209-07:00","invite_email":null,"final_rank":13,"misc":null,"icon":null,"on_waiting_list":false,"invitation_id":null,"group_id":null,"checked_in_at":null,"ranked_member_id":null,"custom_field_response":null,"clinch":null,"integration_uids":null,"challonge_username":null,"challonge_email_address_verified":null,"removable":false,"participatable_or_invitation_attached":false,"confirm_remove":true,"invitation_pending":false,"display_name_with_invitation_email_address":"Artie [RT#0]","email_hash":null,"username":null,"display_name":"Artie [RT#0]","attached_participatable_portrait_url":null,"can_check_in":false,"checked_in":false,"reactivatable":false,"check_in_open":false,"group_player_ids":[],"has_irrelevant_seed":false}},{"participant":{"id":154968946,"tournament_id":10279250,"name":"S1ushie [SLSH#706]","seed":22,"active":true,"created_at":"2021-09-17T18:13:23.919-07:00","updated_at":"2021-09-17T18:14:27.763-07:00","invite_email":null,"final_rank":17,"misc":null,"icon":null,"on_waiting_list":false,"invitation_id":null,"group_id":null,"checked_in_at":null,"ranked_member_id":null,"custom_field_response":null,"clinch":null,"integration_uids":null,"challonge_username":null,"challonge_email_address_verified":null,"removable":false,"participatable_or_invitation_attached":false,"confirm_remove":true,"invitation_pending":false,"display_name_with_invitation_email_address":"S1ushie [SLSH#706]","email_hash":null,"username":null,"display_name":"S1ushie [SLSH#706]","attached_participatable_portrait_url":null,"can_check_in":false,"checked_in":false,"reactivatable":false,"check_in_open":false,"group_player_ids":[],"has_irrelevant_seed":false}}]